README.md
pyproject.toml
ixoncdkingress/__init__.py
ixoncdkingress/__main__.py
ixoncdkingress/py.typed
ixoncdkingress/types.py
ixoncdkingress/utils.py
ixoncdkingress.egg-info/PKG-INFO
ixoncdkingress.egg-info/SOURCES.txt
ixoncdkingress.egg-info/dependency_links.txt
ixoncdkingress.egg-info/requires.txt
ixoncdkingress.egg-info/top_level.txt
ixoncdkingress/cbc/api_client.py
ixoncdkingress/cbc/context.py
ixoncdkingress/cbc/document_db_client.py
ixoncdkingress/cbc/objectstorage/__init__.py
ixoncdkingress/cbc/objectstorage/types.py
ixoncdkingress/function/__init__.py
ixoncdkingress/function/api_client.py
ixoncdkingress/function/caller.py
ixoncdkingress/function/context.py
ixoncdkingress/function/document_db_client.py
ixoncdkingress/function/objectstorage/__init__.py
ixoncdkingress/function/objectstorage/types.py
ixoncdkingress/webserver/__init__.py
ixoncdkingress/webserver/config.py
ixoncdkingress/webserver/form.py
ixoncdkingress/webserver/request.py
ixoncdkingress/webserver/response.py
ixoncdkingress/webserver/servlet.py
ixoncdkingress/webserver/utils.py
ixoncdkingress/webserver/wsgi.py
tests/test___main__.py
tests/test_types.py
tests/test_utils.py