Metadata-Version: 2.1
Name: ixoncdkingress
Version: 0.0.15
Summary: IXON CDK Ingress used in Cloud Functions for the IXON Cloud
Author-email: IXON <development@ixon.cloud>
Project-URL: homepage, https://www.ixon.cloud/
Project-URL: documentation, https://developer.ixon.cloud/
Classifier: Programming Language :: Python :: 3
Requires-Python: >=3.9
Requires-Dist: cryptography~=38.0.3
Requires-Dist: docker>=6.1.3
Requires-Dist: pymongo>=4.4.0
Requires-Dist: requests>=2.28.1
Provides-Extra: development
Requires-Dist: bandit==1.7.4; extra == "development"
Requires-Dist: dominate==2.7.0; extra == "development"
Requires-Dist: ixtest==0.0.20; extra == "development"
Requires-Dist: mock==4.0.3; extra == "development"
Requires-Dist: mypy==0.971; extra == "development"
Requires-Dist: pyfakefs==4.6.3; extra == "development"
Requires-Dist: pylint==2.15.0; extra == "development"
Requires-Dist: pytest==7.1.2; extra == "development"
Requires-Dist: pytest-cov==3.0.0; extra == "development"
Requires-Dist: pytest-integration==0.2.2; extra == "development"
Requires-Dist: pytest-mock==3.8.2; extra == "development"
Requires-Dist: types-requests>=2.28.11.5; extra == "development"
Requires-Dist: wouter==0.0.3; extra == "development"
